purepy/__init__.py
purepy/util.py
purepy-1.0.0.dist-info/LICENSE.txt
purepy-1.0.0.dist-info/METADATA
purepy-1.0.0.dist-info/WHEEL
purepy-1.0.0.dist-info/top_level.txt
purepy-1.0.0.dist-info/RECORD
