Metadata-Version: 2.1
Name: purepy
Version: 1.0.0
Summary: Minor utilites for developing pure virtual classes.
Home-page: https://github.com/mccartnm/purepy
Author: Michael McCartney
Author-email: mccartneyworks@gmail.com
License: MIT
Keywords: preprocess,functions,pure,virtual,metaclass,abstract
Platform: UNKNOWN
Classifier: Development Status :: 4 - Beta
Classifier: Intended Audience :: Developers
Classifier: Topic :: Software Development :: Libraries :: Python Modules
Classifier: License :: OSI Approved :: MIT License
Classifier: Programming Language :: Python :: 2.7
Classifier: Programming Language :: Python :: 3.4
Classifier: Programming Language :: Python :: 3.5
Classifier: Programming Language :: Python :: 3.6
Classifier: Programming Language :: Python :: 3.7
